terraform_snapshot_test/__init__.py
terraform_snapshot_test/utils.py
terraform_snapshot_test-0.0.3.dist-info/licenses/LICENSE
terraform_snapshot_test-0.0.3.dist-info/METADATA
terraform_snapshot_test-0.0.3.dist-info/WHEEL
terraform_snapshot_test-0.0.3.dist-info/top_level.txt
terraform_snapshot_test-0.0.3.dist-info/RECORD
