Metadata-Version: 2.4
Name: terraform-snapshot-test
Version: 0.0.3
Summary: This library provides snapshot testing for Terraform and OpenTofu modules. It generates and compares JSON snapshots of your planned infrastructure changes without deploying anything. Tests run using read-only credentials against provider APIs, giving you fast feedback on whether your code produces the infrastructure you expect.
Author-email: Joao Rodrigues <jrodrigues@joaorodrigues.co.uk>
License-Expression: MIT
Project-URL: Homepage, https://github.com/joaorodrig/terraform-snapshot-test
Project-URL: Issues, https://github.com/joaorodrig/terraform-snapshot-test/issues
Classifier: Programming Language :: Python :: 3
Classifier: Operating System :: POSIX :: Linux
Requires-Python: >=3.12
License-File: LICENSE
Dynamic: license-file
